LICENSE
MANIFEST.in
README.rst
RELEASE-VERSION
setup.py
docs/appresponse.rst
docs/changelog.rst
docs/examples.rst
docs/overview.rst
docs/toc.rst
docs/tutorial.rst
examples/alert_event_report.py
examples/certificate.py
examples/clean_report_instances.py
examples/create_capture_job.py
examples/download.py
examples/general_report.py
examples/json_request.py
examples/list_sources.py
examples/live_report.py
examples/packets_report.py
examples/ssl_keys.py
examples/system_update.py
examples/update_host_groups.py
examples/update_script.py
examples/upload_pcap.py
gitpy_versioning/__init__.py
steelscript/__init__.py
steelscript.appresponse.egg-info/PKG-INFO
steelscript.appresponse.egg-info/SOURCES.txt
steelscript.appresponse.egg-info/dependency_links.txt
steelscript.appresponse.egg-info/entry_points.txt
steelscript.appresponse.egg-info/namespace_packages.txt
steelscript.appresponse.egg-info/not-zip-safe
steelscript.appresponse.egg-info/requires.txt
steelscript.appresponse.egg-info/top_level.txt
steelscript/appresponse/__init__.py
steelscript/appresponse/appfwk/__init__.py
steelscript/appresponse/appfwk/admin.py
steelscript/appresponse/appfwk/fields.py
steelscript/appresponse/appfwk/models.py
steelscript/appresponse/appfwk/plugin.py
steelscript/appresponse/appfwk/datasources/__init__.py
steelscript/appresponse/appfwk/datasources/appresponse.py
steelscript/appresponse/appfwk/devices/__init__.py
steelscript/appresponse/appfwk/devices/appresponse.py
steelscript/appresponse/appfwk/libs/__init__.py
steelscript/appresponse/appfwk/reports/__init__.py
steelscript/appresponse/appfwk/reports/appresponse_asa_overall.py
steelscript/appresponse/appfwk/reports/appresponse_asa_ts.py
steelscript/appresponse/appfwk/reports/appresponse_dbsession_overall.py
steelscript/appresponse/appfwk/reports/appresponse_dbsession_ts.py
steelscript/appresponse/appfwk/reports/appresponse_packets.py
steelscript/appresponse/appfwk/reports/appresponse_packets_dns.py
steelscript/appresponse/appfwk/reports/appresponse_packets_microburst.py
steelscript/appresponse/appfwk/reports/appresponse_packets_microburst_tcp.py
steelscript/appresponse/appfwk/reports/appresponse_packets_search.py
steelscript/appresponse/appfwk/reports/appresponse_packets_tcp_errors.py
steelscript/appresponse/appfwk/reports/appresponse_sql_overall.py
steelscript/appresponse/appfwk/reports/appresponse_sql_ts.py
