Metadata-Version: 1.2
Name: steelscript.appresponse
Version: 2.0.1
Summary: Python modules to interact AppResponse via its REST API
Home-page: http://pythonhosted.org/steelscript
Author: Riverbed Technology
Author-email: eng-github@riverbed.com
License: MIT
Platform: Linux
Platform: Mac OS
Platform: Windows
Classifier: Development Status :: 4 - Beta
Classifier: Intended Audience :: Developers
Classifier: Intended Audience :: Information Technology
Classifier: Intended Audience :: System Administrators
Classifier: License :: OSI Approved :: MIT License
Classifier: Programming Language :: Python :: 3.5
Classifier: Topic :: System :: Networking
Requires-Python: >3.5.0
